MANIFEST.in
README.rst
setup.py
docs/HISTORY.rst
docs/Makefile
docs/api.rst
docs/conf.py
docs/examples.rst
docs/index.rst
docs/websockets.rst
docs/_build/doctrees/HISTORY.doctree
docs/_build/doctrees/api.doctree
docs/_build/doctrees/environment.pickle
docs/_build/doctrees/examples.doctree
docs/_build/doctrees/index.doctree
docs/_build/doctrees/websockets.doctree
docs/_build/html/.buildinfo
docs/_build/html/HISTORY.html
docs/_build/html/api.html
docs/_build/html/examples.html
docs/_build/html/genindex.html
docs/_build/html/index.html
docs/_build/html/objects.inv
docs/_build/html/py-modindex.html
docs/_build/html/search.html
docs/_build/html/searchindex.js
docs/_build/html/websockets.html
docs/_build/html/_sources/HISTORY.txt
docs/_build/html/_sources/api.txt
docs/_build/html/_sources/examples.txt
docs/_build/html/_sources/index.txt
docs/_build/html/_sources/websockets.txt
docs/_build/html/_static/ajax-loader.gif
docs/_build/html/_static/basic.css
docs/_build/html/_static/comment-bright.png
docs/_build/html/_static/comment-close.png
docs/_build/html/_static/comment.png
docs/_build/html/_static/dialog-note.png
docs/_build/html/_static/dialog-seealso.png
docs/_build/html/_static/dialog-topic.png
docs/_build/html/_static/dialog-warning.png
docs/_build/html/_static/doctools.js
docs/_build/html/_static/down-pressed.png
docs/_build/html/_static/down.png
docs/_build/html/_static/epub.css
docs/_build/html/_static/file.png
docs/_build/html/_static/footerbg.png
docs/_build/html/_static/headerbg.png
docs/_build/html/_static/ie6.css
docs/_build/html/_static/jquery.js
docs/_build/html/_static/middlebg.png
docs/_build/html/_static/minus.png
docs/_build/html/_static/plus.png
docs/_build/html/_static/pygments.css
docs/_build/html/_static/pyramid.css
docs/_build/html/_static/pyramid_logo.png
docs/_build/html/_static/searchtools.js
docs/_build/html/_static/transparent.gif
docs/_build/html/_static/underscore.js
docs/_build/html/_static/up-pressed.png
docs/_build/html/_static/up.png
stargate.egg-info/PKG-INFO
stargate.egg-info/SOURCES.txt
stargate.egg-info/dependency_links.txt
stargate.egg-info/entry_points.txt
stargate.egg-info/not-zip-safe
stargate.egg-info/requires.txt
stargate.egg-info/top_level.txt