Metadata-Version: 1.0
Name: stargate
Version: 0.3
Summary: Real time communication for pyramid using WebSockets
Home-page: http://github.com/boothead/stargate
Author: Ben Ford
Author-email: ben@boothead.co.uk
License: MIT
Platform: UNKNOWN
Classifier: Programming Language :: Python
